LICENSE
MANIFEST.in
README.MD
README.md
setup.cfg
setup.py
hmtai/__init__.py
hmtai/hmfull.py
hmtai.egg-info/PKG-INFO
hmtai.egg-info/SOURCES.txt
hmtai.egg-info/dependency_links.txt
hmtai.egg-info/requires.txt
hmtai.egg-info/top_level.txt