Metadata-Version: 2.1
Name: hmtai
Version: 3.1.0
Summary: UNKNOWN
Home-page: https://discord.gg/vJs36ES
Author: NickSaltFoxu
Author-email: thnyawec@gmail.com
License: CC-BY-NC-ND-4.0
Keywords: anime,hentai,nsfw,sfw,images,gifs,wallpaper,discord,ahegao,ass,neko,yuri,panties,thighs,ero,kawaii,cute,waifu,hmtai,zettaiRyouiki,18+,REST,API,Mikun
Platform: UNKNOWN
License-File: LICENSE
